pdoo/__init__.py
pdoo/document.py
pdoo/dom_node.py
pdoo/raw_node.py
pdoo/style.py
pdoo/text_node.py
pdoo-0.1.7.dist-info/LICENSE
pdoo-0.1.7.dist-info/METADATA
pdoo-0.1.7.dist-info/WHEEL
pdoo-0.1.7.dist-info/RECORD
