Metadata-Version: 2.1
Name: pdoo
Version: 0.1.7
Summary: 
License: MIT
Author: tlonny
Requires-Python: >=3.11,<4.0
Classifier: License :: OSI Approved :: MIT License
Classifier: Programming Language :: Python :: 3
Classifier: Programming Language :: Python :: 3.11
Classifier: Programming Language :: Python :: 3.12
